maliang/three/__init__.py
maliang/three/engine.py
maliang/three/geometries.py
maliang_three-1.0.4.dist-info/licenses/LICENSE.txt
maliang_three-1.0.4.dist-info/METADATA
maliang_three-1.0.4.dist-info/WHEEL
maliang_three-1.0.4.dist-info/top_level.txt
maliang_three-1.0.4.dist-info/RECORD
